lotr_sdk/__init__.py
lotr_sdk/base.py
lotr_sdk/movies.py
lotr_sdk/quotes.py
tests/__init__.py
tests/test_endpoints/__init__.py
tests/test_endpoints/test_movie.py
tests/test_endpoints/test_quote.py
gmurtaza_lotr_sdk-0.0.1.dist-info/METADATA
gmurtaza_lotr_sdk-0.0.1.dist-info/WHEEL
gmurtaza_lotr_sdk-0.0.1.dist-info/top_level.txt
gmurtaza_lotr_sdk-0.0.1.dist-info/RECORD
