Metadata-Version: 2.1
Name: gmurtaza-lotr-sdk
Version: 0.0.1
Summary: A Python SDK for the Lord of the Rings API
Author: Ghulam Murtaza
Author-email: gmurtaza.va@gmail.com
Classifier: Intended Audience :: Developers
Classifier: License :: OSI Approved :: MIT License
Classifier: Programming Language :: Python :: 3
Classifier: Programming Language :: Python :: 3.6
Classifier: Programming Language :: Python :: 3.7
Classifier: Programming Language :: Python :: 3.8
Classifier: Programming Language :: Python :: 3.9
Requires-Python: >=3.6
Requires-Dist: requests
